pad_asset_manager/__init__.py
pad_asset_manager/regions/__init__.py
pad_asset_manager/regions/region.py
pad_asset_manager/regions/regions.py
pad_asset_manager/servers/__init__.py
pad_asset_manager/servers/asset.py
pad_asset_manager/servers/extdllist.py
pad_asset_manager/servers/extlist.py
pad_asset_manager/servers/extra.py
pad_asset_manager/servers/http_interface.py
pad_asset_manager/servers/load_servers.py
pad_asset_manager/servers/server.py
pad_asset_manager/servers/servers.py
pad_asset_manager-1.0.2.dist-info/LICENSE
pad_asset_manager-1.0.2.dist-info/METADATA
pad_asset_manager-1.0.2.dist-info/WHEEL
pad_asset_manager-1.0.2.dist-info/top_level.txt
pad_asset_manager-1.0.2.dist-info/RECORD
