Metadata-Version: 2.1
Name: pad-asset-manager
Version: 1.0.2
Summary: An asset and extra manager for Puzzle and Dragons
Home-page: https://github.com/TsubakiBotPad/pad_asset_manager
Author: Aradia Megido#2552 and Cody Watts
Author-email: chasehult@gmail.com
License: MIT
Classifier: Programming Language :: Python :: 3
Classifier: License :: OSI Approved :: MIT License
Classifier: Operating System :: OS Independent
License-File: LICENSE
